artefacts_utils/__init__.py
artefacts_utils/charts.py
artefacts_utils/config.py
artefacts_utils/constants.py
artefacts_utils/gazebo.py
artefacts_utils/helpers.py
artefacts_utils/rosbag.py
artefacts_utils/version.py
artefacts_utils-0.3.8.dist-info/LICENSE
artefacts_utils-0.3.8.dist-info/METADATA
artefacts_utils-0.3.8.dist-info/WHEEL
artefacts_utils-0.3.8.dist-info/top_level.txt
artefacts_utils-0.3.8.dist-info/RECORD
