Metadata-Version: 2.1
Name: artefacts_utils
Version: 0.3.8
Author-email: TN <tomo@artefacts.com>, EP <eric@artefacts.com>
Project-URL: Homepage, https://github.com/art-e-fact/artefacts_utils
Project-URL: Bug Tracker, https://github.com/art-e-fact/artefacts_utils/issues
Classifier: Programming Language :: Python :: 3
Classifier: License :: OSI Approved :: Apache Software License
Classifier: Operating System :: OS Independent
Requires-Python: >=3.10
License-File: LICENSE
Requires-Dist: rosbags
Requires-Dist: rosbags-image
Requires-Dist: plotly
Requires-Dist: artefacts-utils-rosbag-gpl
Provides-Extra: dev
Requires-Dist: build; extra == "dev"
Requires-Dist: pyre-check; extra == "dev"
Requires-Dist: pytest; extra == "dev"
Requires-Dist: pytest-cov; extra == "dev"
Requires-Dist: pytest-env; extra == "dev"
Requires-Dist: pytest-mock; extra == "dev"
Requires-Dist: ruff; extra == "dev"
Requires-Dist: setuptools-scm; extra == "dev"
Requires-Dist: twine; extra == "dev"
